<?xml version="1.0"?>
<pnp:Provisioning xmlns:pnp="http://schemas.dev.office.com/PnP/2020/02/ProvisioningSchema">
  <pnp:Preferences Generator="OfficeDevPnP.Core, Version=3.26.2010.0, Culture=neutral, PublicKeyToken=5e633289e95c321a" />
  <pnp:Templates ID="CONTAINER-TEMPLATE-C36F79857F9B48848981DC1107810786">
    <pnp:ProvisioningTemplate ID="TEMPLATE-C36F79857F9B48848981DC1107810786" Version="1" BaseSiteTemplate="SITEPAGEPUBLISHING#0" Scope="RootSite">
      <pnp:WebSettings NoCrawl="false" WelcomePage="SitePages/Home.aspx" CommentsOnSitePagesDisabled="false" QuickLaunchEnabled="false" SearchScope="DefaultScope" SearchBoxInNavBar="Inherit" />
      <pnp:Lists>
        <pnp:ListInstance Title="QnA" Description="" DocumentTemplate="" TemplateType="100" Url="Lists/QnA" MinorVersionLimit="0" MaxVersionLimit="0" DraftVersionVisibility="0" TemplateFeatureID="00bfea71-de22-43b2-a848-c05709900100" EnableFolderCreation="false" DefaultDisplayFormUrl="{site}/Lists/QnA/DispForm.aspx" DefaultEditFormUrl="{site}/Lists/QnA/EditForm.aspx" DefaultNewFormUrl="{site}/Lists/QnA/NewForm.aspx" ImageUrl="/_layouts/15/images/itgen.png?rev=47" IrmExpire="false" IrmReject="false" IsApplicationList="false" ValidationFormula="" ValidationMessage="">
          <pnp:ContentTypeBindings>
            <pnp:ContentTypeBinding ContentTypeID="0x01" Default="true" />
            <pnp:ContentTypeBinding ContentTypeID="0x0120" />
          </pnp:ContentTypeBindings>
          <pnp:Views>
            <View Name="{123F2792-4D97-41D0-B1BD-65D797C49067}" DefaultView="TRUE" MobileView="TRUE" MobileDefaultView="TRUE" Type="HTML" DisplayName="All Items" Url="{site}/Lists/QnA/AllItems.aspx" Level="1" BaseViewID="1" ContentTypeID="0x" ImageUrl="/_layouts/15/images/generic.png?rev=47">
              <Query />
              <ViewFields>
                <FieldRef Name="LinkTitle" />
                <FieldRef Name="Date" />
                <FieldRef Name="Answer" />
                <FieldRef Name="Choice1" />
                <FieldRef Name="Choice2" />
                <FieldRef Name="Choice3" />
              </ViewFields>
              <RowLimit Paged="TRUE">30</RowLimit>
              <JSLink>clienttemplates.js</JSLink>
              <CustomFormatter />
            </View>
          </pnp:Views>
          <pnp:Fields>
            <Field ClientSideComponentId="00000000-0000-0000-0000-000000000000" DisplayName="QuestionDate" FriendlyDisplayFormat="Disabled" Format="DateOnly" Name="Date" Required="TRUE" Title="QuestionDate" Type="DateTime" ID="{8d676079-c7e5-4bf5-923b-f7c2b0ef1985}" Version="3" StaticName="Date" SourceID="{{listid:QnA}}" ColName="datetime1" RowOrdinal="0" />
            <Field DisplayName="Answer" Format="Dropdown" IsModern="TRUE" MaxLength="255" Name="Answer" Title="Answer" Type="Text" ID="{1405fbcd-e86a-44fd-99c7-48624ced1d05}" SourceID="{{listid:QnA}}" StaticName="Answer" ColName="nvarchar4" RowOrdinal="0" CustomFormatter="" Required="TRUE" EnforceUniqueValues="FALSE" Indexed="FALSE" Version="1" />
            <Field DisplayName="Choice1" Format="Dropdown" IsModern="TRUE" MaxLength="255" Name="Choice1" Title="Choice 1" Type="Text" ID="{5a070fef-bc12-4593-bd2b-aa898c58d276}" SourceID="{{listid:QnA}}" StaticName="Choice1" ColName="nvarchar5" RowOrdinal="0" CustomFormatter="" Required="TRUE" EnforceUniqueValues="FALSE" Indexed="FALSE" Version="2" />
            <Field ClientSideComponentId="00000000-0000-0000-0000-000000000000" CustomFormatter="{&quot;elmType&quot;:&quot;div&quot;,&quot;style&quot;:{&quot;flex-wrap&quot;:&quot;wrap&quot;,&quot;display&quot;:&quot;flex&quot;},&quot;children&quot;:[{&quot;elmType&quot;:&quot;div&quot;,&quot;style&quot;:{&quot;box-sizing&quot;:&quot;border-box&quot;,&quot;padding&quot;:&quot;4px 8px 5px 8px&quot;,&quot;display&quot;:&quot;flex&quot;,&quot;border-radius&quot;:&quot;16px&quot;,&quot;height&quot;:&quot;24px&quot;,&quot;align-items&quot;:&quot;center&quot;,&quot;white-space&quot;:&quot;nowrap&quot;,&quot;overflow&quot;:&quot;hidden&quot;,&quot;margin&quot;:&quot;4px 4px 4px 4px&quot;},&quot;attributes&quot;:{&quot;class&quot;:{&quot;operator&quot;:&quot;:&quot;,&quot;operands&quot;:[{&quot;operator&quot;:&quot;==&quot;,&quot;operands&quot;:[&quot;@currentField&quot;,&quot;Choice 1&quot;]},&quot;sp-css-backgroundColor-blueBackground37&quot;,{&quot;operator&quot;:&quot;:&quot;,&quot;operands&quot;:[{&quot;operator&quot;:&quot;==&quot;,&quot;operands&quot;:[&quot;@currentField&quot;,&quot;Choice 2&quot;]},&quot;sp-css-backgroundColor-successBackground50&quot;,{&quot;operator&quot;:&quot;:&quot;,&quot;operands&quot;:[{&quot;operator&quot;:&quot;==&quot;,&quot;operands&quot;:[&quot;@currentField&quot;,&quot;Choice 3&quot;]},&quot;sp-css-backgroundColor-warningBackground50&quot;,{&quot;operator&quot;:&quot;:&quot;,&quot;operands&quot;:[{&quot;operator&quot;:&quot;==&quot;,&quot;operands&quot;:[&quot;@currentField&quot;,&quot;&quot;]},&quot;&quot;,&quot;sp-field-borderAllRegular sp-field-borderAllSolid sp-css-borderColor-neutralSecondary&quot;]}]}]}]}},&quot;children&quot;:[{&quot;elmType&quot;:&quot;span&quot;,&quot;style&quot;:{&quot;line-height&quot;:&quot;16px&quot;,&quot;height&quot;:&quot;14px&quot;},&quot;attributes&quot;:{&quot;iconName&quot;:{&quot;operator&quot;:&quot;:&quot;,&quot;operands&quot;:[{&quot;operator&quot;:&quot;==&quot;,&quot;operands&quot;:[&quot;@currentField&quot;,&quot;Choice 1&quot;]},&quot;&quot;,{&quot;operator&quot;:&quot;:&quot;,&quot;operands&quot;:[{&quot;operator&quot;:&quot;==&quot;,&quot;operands&quot;:[&quot;@currentField&quot;,&quot;Choice 2&quot;]},&quot;&quot;,{&quot;operator&quot;:&quot;:&quot;,&quot;operands&quot;:[{&quot;operator&quot;:&quot;==&quot;,&quot;operands&quot;:[&quot;@currentField&quot;,&quot;Choice 3&quot;]},&quot;&quot;,{&quot;operator&quot;:&quot;:&quot;,&quot;operands&quot;:[{&quot;operator&quot;:&quot;==&quot;,&quot;operands&quot;:[&quot;@currentField&quot;,&quot;&quot;]},&quot;&quot;,&quot;&quot;]}]}]}]}}},{&quot;elmType&quot;:&quot;span&quot;,&quot;style&quot;:{&quot;overflow&quot;:&quot;hidden&quot;,&quot;text-overflow&quot;:&quot;ellipsis&quot;,&quot;padding&quot;:&quot;0 3px&quot;},&quot;txtContent&quot;:&quot;@currentField&quot;,&quot;attributes&quot;:{&quot;class&quot;:{&quot;operator&quot;:&quot;:&quot;,&quot;operands&quot;:[{&quot;operator&quot;:&quot;==&quot;,&quot;operands&quot;:[&quot;@currentField&quot;,&quot;Choice 1&quot;]},&quot;&quot;,{&quot;operator&quot;:&quot;:&quot;,&quot;operands&quot;:[{&quot;operator&quot;:&quot;==&quot;,&quot;operands&quot;:[&quot;@currentField&quot;,&quot;Choice 2&quot;]},&quot;&quot;,{&quot;operator&quot;:&quot;:&quot;,&quot;operands&quot;:[{&quot;operator&quot;:&quot;==&quot;,&quot;operands&quot;:[&quot;@currentField&quot;,&quot;Choice 3&quot;]},&quot;&quot;,{&quot;operator&quot;:&quot;:&quot;,&quot;operands&quot;:[{&quot;operator&quot;:&quot;==&quot;,&quot;operands&quot;:[&quot;@currentField&quot;,&quot;&quot;]},&quot;&quot;,&quot;&quot;]}]}]}]}}}]}],&quot;templateId&quot;:&quot;BgColorChoicePill&quot;}" DisplayName="Choice2" Format="Dropdown" MaxLength="255" Name="Choice2" Title="Choice2" Type="Text" ID="{13616441-161c-48c6-b1cb-4baa912899a3}" Version="4" StaticName="Choice2" SourceID="{{listid:QnA}}" ColName="nvarchar6" RowOrdinal="0" />
            <Field ClientSideComponentId="00000000-0000-0000-0000-000000000000" DisplayName="Choice3" Format="Dropdown" MaxLength="255" Name="Choice3" Title="Choice3" Type="Text" ID="{4fdf9d6e-ac86-48b8-bcde-e5537406fd85}" Version="2" StaticName="Choice3" SourceID="{{listid:QnA}}" ColName="nvarchar7" RowOrdinal="0" />
          </pnp:Fields>
          <pnp:DataRows KeyColumn="Title" UpdateBehavior="Overwrite">
            <pnp:DataRow>
              <pnp:DataValue FieldName="ContentTypeId">0x01009219F59C9BF692479E0D35E58666E6E1</pnp:DataValue>
              <pnp:DataValue FieldName="Title">What is the keyboard shortcut to mute/unmute yourself in teams ?</pnp:DataValue>
              <pnp:DataValue FieldName="_ModerationComments" />
              <pnp:DataValue FieldName="File_x0020_Type" />
              <pnp:DataValue FieldName="ComplianceAssetId" />
              <pnp:DataValue FieldName="Date">2021-02-10T23:00:00Z</pnp:DataValue>
              <pnp:DataValue FieldName="Answer">Ctrl + Shift +M</pnp:DataValue>
              <pnp:DataValue FieldName="Choice1">Ctrl + M</pnp:DataValue>
              <pnp:DataValue FieldName="Choice2">Ctrl + Shift +U</pnp:DataValue>
              <pnp:DataValue FieldName="Choice3">Ctrl + Shift +M</pnp:DataValue>
              </pnp:DataRow>
            <pnp:DataRow>
              <pnp:DataValue FieldName="ContentTypeId">0x01009219F59C9BF692479E0D35E58666E6E1</pnp:DataValue>
              <pnp:DataValue FieldName="Title">What is the keyboard shortcut to quick access the search bar at the top of teams ?</pnp:DataValue>
              <pnp:DataValue FieldName="_ModerationComments" />
              <pnp:DataValue FieldName="File_x0020_Type" />
              <pnp:DataValue FieldName="ComplianceAssetId" />
              <pnp:DataValue FieldName="Date">2021-01-10T23:00:00Z</pnp:DataValue>
              <pnp:DataValue FieldName="Answer"> Ctrl + E</pnp:DataValue>
              <pnp:DataValue FieldName="Choice1"> Ctrl + S</pnp:DataValue>
              <pnp:DataValue FieldName="Choice2"> Ctrl + E</pnp:DataValue>
              <pnp:DataValue FieldName="Choice3"> Ctrl + Shift + E</pnp:DataValue>
                  </pnp:DataRow>
            <pnp:DataRow>
              <pnp:DataValue FieldName="ContentTypeId">0x01009219F59C9BF692479E0D35E58666E6E1</pnp:DataValue>
              <pnp:DataValue FieldName="Title">If you can’t find the right emoji in Teams emoji library  what is a shortcut to find more ?</pnp:DataValue>
              <pnp:DataValue FieldName="_ModerationComments" />
              <pnp:DataValue FieldName="File_x0020_Type" />
              <pnp:DataValue FieldName="ComplianceAssetId" />
              <pnp:DataValue FieldName="Date">2021-01-12T23:00:00Z</pnp:DataValue>
              <pnp:DataValue FieldName="Answer"> Type a colon “:” immediately followed by a word </pnp:DataValue>
              <pnp:DataValue FieldName="Choice1"> Type a semicolon “;” immediately followed by a word </pnp:DataValue>
              <pnp:DataValue FieldName="Choice2"> Type a dot “.” immediately followed by a word </pnp:DataValue>
              <pnp:DataValue FieldName="Choice3"> Type a colon “:” immediately followed by a word </pnp:DataValue>
             </pnp:DataRow>
            <pnp:DataRow>
              <pnp:DataValue FieldName="ContentTypeId">0x01009219F59C9BF692479E0D35E58666E6E1</pnp:DataValue>
              <pnp:DataValue FieldName="Title">What is the keyboard shortcut to attach a file ?</pnp:DataValue>
              <pnp:DataValue FieldName="_ModerationComments" />
              <pnp:DataValue FieldName="File_x0020_Type" />
              <pnp:DataValue FieldName="ComplianceAssetId" />
              <pnp:DataValue FieldName="Date">2021-01-12T23:00:00Z</pnp:DataValue>
              <pnp:DataValue FieldName="Answer">Ctrl + O</pnp:DataValue>
              <pnp:DataValue FieldName="Choice1">Ctrl + O</pnp:DataValue>
              <pnp:DataValue FieldName="Choice2">Ctrl + F</pnp:DataValue>
              <pnp:DataValue FieldName="Choice3">Ctrl + A</pnp:DataValue>
             </pnp:DataRow>
            <pnp:DataRow>
              <pnp:DataValue FieldName="ContentTypeId">0x01009219F59C9BF692479E0D35E58666E6E1</pnp:DataValue>
              <pnp:DataValue FieldName="Title">what is the keyboard shortcut to access Calendar in teams ?</pnp:DataValue>
              <pnp:DataValue FieldName="_ModerationComments" />
              <pnp:DataValue FieldName="File_x0020_Type" />
              <pnp:DataValue FieldName="ComplianceAssetId" />
              <pnp:DataValue FieldName="Date">2021-01-13T23:00:00Z</pnp:DataValue>
              <pnp:DataValue FieldName="Answer">Ctrl + 4</pnp:DataValue>
              <pnp:DataValue FieldName="Choice1">Ctrl + 4</pnp:DataValue>
              <pnp:DataValue FieldName="Choice2">Ctrl + C</pnp:DataValue>
              <pnp:DataValue FieldName="Choice3">Ctrl + Alt + C</pnp:DataValue>
           </pnp:DataRow>
            <pnp:DataRow>
              <pnp:DataValue FieldName="ContentTypeId">0x01009219F59C9BF692479E0D35E58666E6E1</pnp:DataValue>
              <pnp:DataValue FieldName="Title">What is the limit for file upload in Team ?</pnp:DataValue>
              <pnp:DataValue FieldName="_ModerationComments" />
              <pnp:DataValue FieldName="File_x0020_Type" />
              <pnp:DataValue FieldName="ComplianceAssetId" />
              <pnp:DataValue FieldName="Date">2021-01-16T23:00:00Z</pnp:DataValue>
              <pnp:DataValue FieldName="Answer">15 GB per file</pnp:DataValue>
              <pnp:DataValue FieldName="Choice1">100 GB per file</pnp:DataValue>
              <pnp:DataValue FieldName="Choice2">15 GB per file</pnp:DataValue>
              <pnp:DataValue FieldName="Choice3">100 MB per file</pnp:DataValue>
               </pnp:DataRow>
            <pnp:DataRow>
              <pnp:DataValue FieldName="ContentTypeId">0x01009219F59C9BF692479E0D35E58666E6E1</pnp:DataValue>
              <pnp:DataValue FieldName="Title">What is the limit of attendees in Team meetings?</pnp:DataValue>
              <pnp:DataValue FieldName="_ModerationComments" />
              <pnp:DataValue FieldName="File_x0020_Type" />
              <pnp:DataValue FieldName="ComplianceAssetId" />
              <pnp:DataValue FieldName="Date">2021-01-17T23:00:00Z</pnp:DataValue>
              <pnp:DataValue FieldName="Answer">350</pnp:DataValue>
              <pnp:DataValue FieldName="Choice1">350</pnp:DataValue>
              <pnp:DataValue FieldName="Choice2">300</pnp:DataValue>
              <pnp:DataValue FieldName="Choice3">250</pnp:DataValue>
            </pnp:DataRow>
            <pnp:DataRow>
              <pnp:DataValue FieldName="ContentTypeId">0x01009219F59C9BF692479E0D35E58666E6E1</pnp:DataValue>
              <pnp:DataValue FieldName="Title">What is the maximum number of members I can have in a team?</pnp:DataValue>
              <pnp:DataValue FieldName="_ModerationComments" />
              <pnp:DataValue FieldName="File_x0020_Type" />
              <pnp:DataValue FieldName="ComplianceAssetId" />
              <pnp:DataValue FieldName="Date">2021-01-18T23:00:00Z</pnp:DataValue>
              <pnp:DataValue FieldName="Answer">10000</pnp:DataValue>
              <pnp:DataValue FieldName="Choice1">1000</pnp:DataValue>
              <pnp:DataValue FieldName="Choice2">14000</pnp:DataValue>
              <pnp:DataValue FieldName="Choice3">10000</pnp:DataValue>
            </pnp:DataRow>
            <pnp:DataRow>
              <pnp:DataValue FieldName="ContentTypeId">0x01009219F59C9BF692479E0D35E58666E6E1</pnp:DataValue>
              <pnp:DataValue FieldName="Title">What is the maximum length of the Audio Conferencing meetings?</pnp:DataValue>
              <pnp:DataValue FieldName="_ModerationComments" />
              <pnp:DataValue FieldName="File_x0020_Type" />
              <pnp:DataValue FieldName="ComplianceAssetId" />
              <pnp:DataValue FieldName="Date">2021-01-19T23:00:00Z</pnp:DataValue>
              <pnp:DataValue FieldName="Answer">24 hours</pnp:DataValue>
              <pnp:DataValue FieldName="Choice1">24 hours</pnp:DataValue>
              <pnp:DataValue FieldName="Choice2">10 hours</pnp:DataValue>
              <pnp:DataValue FieldName="Choice3">14 hours</pnp:DataValue>
            </pnp:DataRow>
            <pnp:DataRow>
              <pnp:DataValue FieldName="ContentTypeId">0x01009219F59C9BF692479E0D35E58666E6E1</pnp:DataValue>
              <pnp:DataValue FieldName="Title">How much OneDrive storage do I get with Office 365?</pnp:DataValue>
              <pnp:DataValue FieldName="_ModerationComments" />
              <pnp:DataValue FieldName="File_x0020_Type" />
              <pnp:DataValue FieldName="ComplianceAssetId" />
              <pnp:DataValue FieldName="Date">2021-01-20T23:00:00Z</pnp:DataValue>
              <pnp:DataValue FieldName="Answer">1 TB</pnp:DataValue>
              <pnp:DataValue FieldName="Choice1">100 GB</pnp:DataValue>
              <pnp:DataValue FieldName="Choice2">1 GB</pnp:DataValue>
              <pnp:DataValue FieldName="Choice3">1 TB</pnp:DataValue>
            </pnp:DataRow>
            <pnp:DataRow>
              <pnp:DataValue FieldName="ContentTypeId">0x01009219F59C9BF692479E0D35E58666E6E1</pnp:DataValue>
              <pnp:DataValue FieldName="Title">How many total phone participants can I have in meetings?</pnp:DataValue>
              <pnp:DataValue FieldName="_ModerationComments" />
              <pnp:DataValue FieldName="File_x0020_Type" />
              <pnp:DataValue FieldName="ComplianceAssetId" />
              <pnp:DataValue FieldName="Date">2021-01-23T23:00:00Z</pnp:DataValue>
              <pnp:DataValue FieldName="Answer">250</pnp:DataValue>
              <pnp:DataValue FieldName="Choice1">100</pnp:DataValue>
              <pnp:DataValue FieldName="Choice2">250</pnp:DataValue>
              <pnp:DataValue FieldName="Choice3">25</pnp:DataValue>
            </pnp:DataRow>
            <pnp:DataRow>
              <pnp:DataValue FieldName="ContentTypeId">0x01009219F59C9BF692479E0D35E58666E6E1</pnp:DataValue>
              <pnp:DataValue FieldName="Title">How to schedule a meeting in teams?</pnp:DataValue>
              <pnp:DataValue FieldName="_ModerationComments" />
              <pnp:DataValue FieldName="File_x0020_Type" />
              <pnp:DataValue FieldName="ComplianceAssetId" />
              <pnp:DataValue FieldName="Date">2021-01-24T23:00:00Z</pnp:DataValue>
              <pnp:DataValue FieldName="Answer">Both</pnp:DataValue>
              <pnp:DataValue FieldName="Choice1">Microsoft Teams</pnp:DataValue>
              <pnp:DataValue FieldName="Choice2">Outlook</pnp:DataValue>
              <pnp:DataValue FieldName="Choice3">Both</pnp:DataValue>
            </pnp:DataRow>
            <pnp:DataRow>
              <pnp:DataValue FieldName="ContentTypeId">0x01009219F59C9BF692479E0D35E58666E6E1</pnp:DataValue>
              <pnp:DataValue FieldName="Title">How to mention someone in a conversation</pnp:DataValue>
              <pnp:DataValue FieldName="_ModerationComments" />
              <pnp:DataValue FieldName="File_x0020_Type" />
              <pnp:DataValue FieldName="ComplianceAssetId" />
              <pnp:DataValue FieldName="Date">2021-01-25T23:00:00Z</pnp:DataValue>
              <pnp:DataValue FieldName="Answer">@ followed by the name</pnp:DataValue>
              <pnp:DataValue FieldName="Choice1">@ followed by the name of the user</pnp:DataValue>
              <pnp:DataValue FieldName="Choice2"># followed by the name of the user</pnp:DataValue>
              <pnp:DataValue FieldName="Choice3">simply type the name of the user</pnp:DataValue>
            </pnp:DataRow>
            <pnp:DataRow>
              <pnp:DataValue FieldName="ContentTypeId">0x01009219F59C9BF692479E0D35E58666E6E1</pnp:DataValue>
              <pnp:DataValue FieldName="Title">How can i access Microsoft Teams ?</pnp:DataValue>
              <pnp:DataValue FieldName="_ModerationComments" />
              <pnp:DataValue FieldName="File_x0020_Type" />
              <pnp:DataValue FieldName="ComplianceAssetId" />
              <pnp:DataValue FieldName="Date">2021-01-26T23:00:00Z</pnp:DataValue>
              <pnp:DataValue FieldName="Answer">Both</pnp:DataValue>
              <pnp:DataValue FieldName="Choice1">Desktop Version</pnp:DataValue>
              <pnp:DataValue FieldName="Choice2">Browser</pnp:DataValue>
              <pnp:DataValue FieldName="Choice3">Both</pnp:DataValue>
            </pnp:DataRow>
            <pnp:DataRow>
              <pnp:DataValue FieldName="ContentTypeId">0x01009219F59C9BF692479E0D35E58666E6E1</pnp:DataValue>
              <pnp:DataValue FieldName="Title">What is the keyboard shortcut to start a new chat in teams ?</pnp:DataValue>
              <pnp:DataValue FieldName="_ModerationComments" />
              <pnp:DataValue FieldName="File_x0020_Type" />
              <pnp:DataValue FieldName="ComplianceAssetId" />
              <pnp:DataValue FieldName="Date">2021-01-27T23:00:00Z</pnp:DataValue>
              <pnp:DataValue FieldName="Answer">Ctrl + N</pnp:DataValue>
              <pnp:DataValue FieldName="Choice1">Ctrl + N</pnp:DataValue>
              <pnp:DataValue FieldName="Choice2">Ctrl + Shift + N</pnp:DataValue>
              <pnp:DataValue FieldName="Choice3">Ctrl + Shift + C</pnp:DataValue>
            </pnp:DataRow>
            <pnp:DataRow>
              <pnp:DataValue FieldName="ContentTypeId">0x01009219F59C9BF692479E0D35E58666E6E1</pnp:DataValue>
              <pnp:DataValue FieldName="Title">What kind of teams you can create in Microsoft Teams?</pnp:DataValue>
              <pnp:DataValue FieldName="_ModerationComments" />
              <pnp:DataValue FieldName="File_x0020_Type" />
              <pnp:DataValue FieldName="ComplianceAssetId" />
              <pnp:DataValue FieldName="Date">2021-01-30T23:00:00Z</pnp:DataValue>
              <pnp:DataValue FieldName="Answer">Private and Public</pnp:DataValue>
              <pnp:DataValue FieldName="Choice1">Private and Public</pnp:DataValue>
              <pnp:DataValue FieldName="Choice2">Private , Public and Organizational</pnp:DataValue>
              <pnp:DataValue FieldName="Choice3">Private , Personal and Public</pnp:DataValue>
            </pnp:DataRow>
            <pnp:DataRow>
              <pnp:DataValue FieldName="ContentTypeId">0x01009219F59C9BF692479E0D35E58666E6E1</pnp:DataValue>
              <pnp:DataValue FieldName="Title">Which technology is used by organizations to create websites and use it as a secure place to store, organize, share, and access information from almost any device ?</pnp:DataValue>
              <pnp:DataValue FieldName="_ModerationComments" />
              <pnp:DataValue FieldName="File_x0020_Type" />
              <pnp:DataValue FieldName="ComplianceAssetId" />
              <pnp:DataValue FieldName="Date">2021-01-31T23:00:00Z</pnp:DataValue>
              <pnp:DataValue FieldName="Answer">SharePoint</pnp:DataValue>
              <pnp:DataValue FieldName="Choice1">Teams</pnp:DataValue>
              <pnp:DataValue FieldName="Choice2">OneDrive</pnp:DataValue>
              <pnp:DataValue FieldName="Choice3">SharePoint</pnp:DataValue>
            </pnp:DataRow>
            <pnp:DataRow>
              <pnp:DataValue FieldName="ContentTypeId">0x01009219F59C9BF692479E0D35E58666E6E1</pnp:DataValue>
              <pnp:DataValue FieldName="Title">Which technology is used as online storage service that you can use to store documents, notes, photos, music, videos, or other types of files ?</pnp:DataValue>
              <pnp:DataValue FieldName="_ModerationComments" />
              <pnp:DataValue FieldName="File_x0020_Type" />
              <pnp:DataValue FieldName="ComplianceAssetId" />
              <pnp:DataValue FieldName="Date">2021-02-01T23:00:00Z</pnp:DataValue>
              <pnp:DataValue FieldName="Answer">OneDrive</pnp:DataValue>
              <pnp:DataValue FieldName="Choice1">SharePoint</pnp:DataValue>
              <pnp:DataValue FieldName="Choice2">OneDrive</pnp:DataValue>
              <pnp:DataValue FieldName="Choice3">Teams</pnp:DataValue>
            </pnp:DataRow>
            <pnp:DataRow>
              <pnp:DataValue FieldName="ContentTypeId">0x01009219F59C9BF692479E0D35E58666E6E1</pnp:DataValue>
              <pnp:DataValue FieldName="Title">which product is used to automate business processes ?</pnp:DataValue>
              <pnp:DataValue FieldName="_ModerationComments" />
              <pnp:DataValue FieldName="File_x0020_Type" />
              <pnp:DataValue FieldName="ComplianceAssetId" />
              <pnp:DataValue FieldName="Date">2021-02-02T23:00:00Z</pnp:DataValue>
              <pnp:DataValue FieldName="Answer">Power Automate</pnp:DataValue>
              <pnp:DataValue FieldName="Choice1">Power Automate</pnp:DataValue>
              <pnp:DataValue FieldName="Choice2">PowerApps</pnp:DataValue>
              <pnp:DataValue FieldName="Choice3">Planner</pnp:DataValue>
            </pnp:DataRow>
            <pnp:DataRow>
              <pnp:DataValue FieldName="ContentTypeId">0x01009219F59C9BF692479E0D35E58666E6E1</pnp:DataValue>
              <pnp:DataValue FieldName="Title">Which product is used as electronic forms to capture inputs from users and can be used from any device ?</pnp:DataValue>
              <pnp:DataValue FieldName="_ModerationComments" />
              <pnp:DataValue FieldName="File_x0020_Type" />
              <pnp:DataValue FieldName="ComplianceAssetId" />
              <pnp:DataValue FieldName="Date">2021-01-27T23:00:00Z</pnp:DataValue>
              <pnp:DataValue FieldName="Answer">PowerApps</pnp:DataValue>
              <pnp:DataValue FieldName="Choice1">Power Automate</pnp:DataValue>
              <pnp:DataValue FieldName="Choice2">PowerApps</pnp:DataValue>
              <pnp:DataValue FieldName="Choice3">InfoPath</pnp:DataValue>
            </pnp:DataRow>
          </pnp:DataRows>
        </pnp:ListInstance>
        <pnp:ListInstance Title="userPointsList" Description="" DocumentTemplate="" TemplateType="100" Url="Lists/userPointsList" MinorVersionLimit="0" MaxVersionLimit="0" DraftVersionVisibility="0" TemplateFeatureID="00bfea71-de22-43b2-a848-c05709900100" EnableFolderCreation="false" DefaultDisplayFormUrl="{site}/Lists/userPointsList/DispForm.aspx" DefaultEditFormUrl="{site}/Lists/userPointsList/EditForm.aspx" DefaultNewFormUrl="{site}/Lists/userPointsList/NewForm.aspx" ImageUrl="/_layouts/15/images/itgen.png?rev=47" IrmExpire="false" IrmReject="false" IsApplicationList="false" ValidationFormula="" ValidationMessage="">
          <pnp:ContentTypeBindings>
            <pnp:ContentTypeBinding ContentTypeID="0x01" Default="true" />
            <pnp:ContentTypeBinding ContentTypeID="0x0120" />
          </pnp:ContentTypeBindings>
          <pnp:Views>
            <View Name="{80F779B2-CBC3-4025-A4E2-729DD89FC9EB}" DefaultView="TRUE" MobileView="TRUE" MobileDefaultView="TRUE" Type="HTML" DisplayName="All Items" Url="{site}/Lists/userPointsList/AllItems.aspx" Level="1" BaseViewID="1" ContentTypeID="0x" ImageUrl="/_layouts/15/images/generic.png?rev=47">
              <Query />
              <ViewFields>
                <FieldRef Name="LinkTitle" />
                <FieldRef Name="Date" />
                <FieldRef Name="Points" />
              </ViewFields>
              <RowLimit Paged="TRUE">30</RowLimit>
              <JSLink>clienttemplates.js</JSLink>
              <CustomFormatter />
            </View>
          </pnp:Views>
          <pnp:Fields>
            <Field DisplayName="Date" FriendlyDisplayFormat="Disabled" Format="DateOnly" IsModern="TRUE" Name="Date" Title="Date" Type="DateTime" ID="{cf2a0ba8-b78d-45b1-8fc2-c32f004d5ece}" SourceID="{{listid:userPointsList}}" StaticName="Date" ColName="datetime1" RowOrdinal="0" />
            <Field CommaSeparator="TRUE" DisplayName="Points" Format="Dropdown" IsModern="TRUE" Name="Points" Percentage="FALSE" Title="Points" Type="Number" ID="{02225617-298d-4092-9f19-d018b85b5bdb}" SourceID="{{listid:userPointsList}}" StaticName="Points" ColName="float1" RowOrdinal="0" />
          </pnp:Fields>
          <pnp:Security>
            <pnp:BreakRoleInheritance CopyRoleAssignments="false" ClearSubscopes="false">
              <pnp:RoleAssignment Principal="{associatedownergroupid}" RoleDefinition="Full Control" />
              <pnp:RoleAssignment Principal="{associatedvisitorgroupid}" RoleDefinition="Read" />
              <pnp:RoleAssignment Principal="{associatedmembergroupid}" RoleDefinition="Edit" />
              <pnp:RoleAssignment Principal="{associatedmembergroupid}" RoleDefinition="Contribute" />
            </pnp:BreakRoleInheritance>
          </pnp:Security>
        </pnp:ListInstance>
      </pnp:Lists>
      <pnp:Features>
        <pnp:SiteFeatures>
          <pnp:Feature ID="232b3f94-9d6e-4ed6-8d55-04d5a44ac449" />
          <pnp:Feature ID="94280101-dc63-4b83-842a-8707b1afb62d" />
        </pnp:SiteFeatures>
        <pnp:WebFeatures>
          <pnp:Feature ID="8c6f9096-388d-4eed-96ff-698b3ec46fc4" />
        </pnp:WebFeatures>
      </pnp:Features>
      <pnp:Files>
        <pnp:File Src="SiteAssets/SitePages/RamadanCalendar/75083-Ramadan-marketing-ideas---increase-your-Muslim-customers.jpeg" Folder="SiteAssets/SitePages/RamadanCalendar" Overwrite="true" Level="Published" />
        <pnp:File Src="SiteAssets/SitePages/RamadanCalendar/54796-images.jpg" Folder="SiteAssets/SitePages/RamadanCalendar" Overwrite="true" Level="Published" />
        <pnp:File Src="SiteAssets/SitePages/Home/70624508Ramadan-delivery.jpg" Folder="SiteAssets/SitePages/Home" Overwrite="true" Level="Published" />
        <pnp:File Src="SiteAssets/SitePages/RamadanCalendar/157398fcb4406194c24cc63c46da662883043.jpg" Folder="SiteAssets/SitePages/RamadanCalendar" Overwrite="true" Level="Published" />
        <pnp:File Src="SiteAssets/SitePages/RamadanCalendar/2608mobile_banner.jpg" Folder="SiteAssets/SitePages/RamadanCalendar" Overwrite="true" Level="Published" />
        <pnp:File Src="SiteAssets/SitePages/RamadanCalendar/745414elHFkW.jpg" Folder="SiteAssets/SitePages/RamadanCalendar" Overwrite="true" Level="Published" />
        <pnp:File Src="SiteAssets/SitePages/RamadanCalendar/80488WhatsApp-Image-2018-10-18-at-8.06.23-PM.jpeg" Folder="SiteAssets/SitePages/RamadanCalendar" Overwrite="true" Level="Published" />
        <pnp:File Src="SiteAssets/SitePages/Mac-n-Cheese/94877-chicago-foodie-girl--Southport-and-Irving--SIP-.jpeg" Folder="SiteAssets/SitePages/Mac-n-Cheese" Overwrite="true" Level="Published" />
        <pnp:File Src="SiteAssets/SitePages/Donate/63981-Ramadan-Kareem-Free-Stock-Photo---Public-Domain-Pictures.jpeg" Folder="SiteAssets/SitePages/Donate" Overwrite="true" Level="Published" />
        <pnp:File Src="SiteAssets/SitePages/Donate/933364814Slider-810x425pix.jpg" Folder="SiteAssets/SitePages/Donate" Overwrite="true" Level="Published" />
        <pnp:File Src="SiteAssets/SitePages/Donate/3418061374donation-to-57357-hospital.jpg" Folder="SiteAssets/SitePages/Donate" Overwrite="true" Level="Published" />
        <pnp:File Src="SiteAssets/SitePages/Fazoora/57327-decoration-3346133_1920.jpg" Folder="SiteAssets/SitePages/Fazoora" Overwrite="true" Level="Published" />
      </pnp:Files>
      <pnp:ClientSidePages>
        <pnp:ClientSidePage PromoteAsNewsArticle="false" PromoteAsTemplate="false" Overwrite="true" Layout="Home" EnableComments="false" Title="Home" ThumbnailUrl="" PageName="Home.aspx">
          <pnp:Header Type="Default" LayoutType="FullWidthImage" TextAlignment="Center" ShowTopicHeader="false" ShowPublishDate="false" TopicHeader="" AlternativeText="" Authors="[]" AuthorByLine="[]" AuthorByLineId="-1" />
          <pnp:Sections>
            <pnp:Section Order="1" Type="TwoColumn">
              <pnp:Controls>
                <pnp:CanvasControl WebPartType="Image" JsonControlData="{&quot;id&quot;: &quot;d1d91016-032f-456d-98a4-721247c305e8&quot;, &quot;instanceId&quot;: &quot;ec9093f3-6764-4238-abc0-a13c6edb9f89&quot;, &quot;title&quot;: &quot;Image&quot;, &quot;description&quot;: &quot;Image&quot;, &quot;dataVersion&quot;: &quot;1.9&quot;, &quot;properties&quot;: {&quot;imageSourceType&quot;:2,&quot;captionText&quot;:&quot;&quot;,&quot;altText&quot;:&quot;&quot;,&quot;linkUrl&quot;:&quot;&quot;,&quot;overlayText&quot;:&quot;&quot;,&quot;fileName&quot;:&quot;&quot;,&quot;siteId&quot;:&quot;{sitecollectionid}&quot;,&quot;webId&quot;:&quot;{siteid}&quot;,&quot;listId&quot;:&quot;{listid:Site Assets}&quot;,&quot;uniqueId&quot;:&quot;{fileuniqueid:SiteAssets/SitePages/RamadanCalendar/75083-Ramadan-marketing-ideas---increase-your-Muslim-customers.jpeg}&quot;,&quot;imgWidth&quot;:540,&quot;imgHeight&quot;:444,&quot;alignment&quot;:&quot;Center&quot;,&quot;fixAspectRatio&quot;:false,&quot;isFullWidth&quot;:false}, &quot;serverProcessedContent&quot;: {&quot;htmlStrings&quot;:{},&quot;searchablePlainTexts&quot;:{},&quot;imageSources&quot;:{&quot;imageSource&quot;:&quot;{site}/SiteAssets/SitePages/RamadanCalendar/75083-Ramadan-marketing-ideas---increase-your-Muslim-customers.jpeg&quot;},&quot;links&quot;:{},&quot;customMetadata&quot;:{&quot;imageSource&quot;:{&quot;siteId&quot;:&quot;{sitecollectionid}&quot;,&quot;webId&quot;:&quot;{siteid}&quot;,&quot;listId&quot;:&quot;{listid:Site Assets}&quot;,&quot;uniqueId&quot;:&quot;{fileuniqueid:SiteAssets/SitePages/RamadanCalendar/75083-Ramadan-marketing-ideas---increase-your-Muslim-customers.jpeg}&quot;,&quot;width&quot;:540,&quot;height&quot;:444}}}, &quot;dynamicDataPaths&quot;: {}, &quot;dynamicDataValues&quot;: {}}" ControlId="d1d91016-032f-456d-98a4-721247c305e8" Order="1" Column="1" />
                <pnp:CanvasControl WebPartType="Text" ControlId="cd2131e7-c545-47fc-83d0-b094c1255e96" Order="1" Column="2">
                  <pnp:CanvasControlProperties>
                    <pnp:CanvasControlProperty Key="Text" Value="&lt;p&gt;Ramadan&amp;nbsp;does what perhaps might normally take weeks to organize, that is gather&amp;nbsp;families&amp;nbsp;for a meal. It is custom to sit together for the sunset meal as a&amp;nbsp;family&amp;nbsp;when breaking your fast, and it gives the&amp;nbsp;family&amp;nbsp;an opportunity to catch up with each other's news and enjoy each other, to connect with each other.&lt;/p&gt;&lt;p&gt;&lt;br&gt;&lt;/p&gt;&lt;p&gt;&amp;nbsp;It's a moment for &lt;em&gt;spiritually uplifting&lt;/em&gt;.&lt;/p&gt;" />
                  </pnp:CanvasControlProperties>
                </pnp:CanvasControl>
              </pnp:Controls>
            </pnp:Section>
            <pnp:Section Order="2" Type="TwoColumn">
              <pnp:Controls>
                <pnp:CanvasControl WebPartType="Image" JsonControlData="{&quot;id&quot;: &quot;d1d91016-032f-456d-98a4-721247c305e8&quot;, &quot;instanceId&quot;: &quot;b1a72122-f65e-4119-b360-baf3265b5ab4&quot;, &quot;title&quot;: &quot;Image&quot;, &quot;description&quot;: &quot;Image&quot;, &quot;dataVersion&quot;: &quot;1.9&quot;, &quot;properties&quot;: {&quot;imageSourceType&quot;:2,&quot;captionText&quot;:&quot;&quot;,&quot;altText&quot;:&quot;&quot;,&quot;linkUrl&quot;:&quot;&quot;,&quot;overlayText&quot;:&quot;&quot;,&quot;fileName&quot;:&quot;images.jpg&quot;,&quot;siteId&quot;:&quot;{sitecollectionid}&quot;,&quot;webId&quot;:&quot;{siteid}&quot;,&quot;listId&quot;:&quot;{listid:Site Assets}&quot;,&quot;uniqueId&quot;:&quot;{fileuniqueid:SiteAssets/SitePages/RamadanCalendar/54796-images.jpg}&quot;,&quot;imgWidth&quot;:276,&quot;imgHeight&quot;:183,&quot;alignment&quot;:&quot;Center&quot;,&quot;fixAspectRatio&quot;:false}, &quot;serverProcessedContent&quot;: {&quot;htmlStrings&quot;:{},&quot;searchablePlainTexts&quot;:{},&quot;imageSources&quot;:{&quot;imageSource&quot;:&quot;{site}/SiteAssets/SitePages/RamadanCalendar/54796-images.jpg&quot;},&quot;links&quot;:{},&quot;customMetadata&quot;:{&quot;imageSource&quot;:{&quot;siteId&quot;:&quot;{sitecollectionid}&quot;,&quot;webId&quot;:&quot;{siteid}&quot;,&quot;listId&quot;:&quot;{listid:Site Assets}&quot;,&quot;uniqueId&quot;:&quot;{fileuniqueid:SiteAssets/SitePages/RamadanCalendar/54796-images.jpg}&quot;,&quot;width&quot;:276,&quot;height&quot;:183}}}, &quot;dynamicDataPaths&quot;: {}, &quot;dynamicDataValues&quot;: {}}" ControlId="d1d91016-032f-456d-98a4-721247c305e8" Order="1" Column="1" />
                <pnp:CanvasControl WebPartType="Text" ControlId="32ce176e-b2cd-4021-9471-730bc872fd66" Order="1" Column="2">
                  <pnp:CanvasControlProperties>
                    <pnp:CanvasControlProperty Key="Text" Value="&lt;p&gt;&lt;br&gt;&lt;/p&gt;&lt;h3&gt;&amp;nbsp;Ramadan Competition!&amp;nbsp;&amp;nbsp;🌙&amp;nbsp;&lt;/h3&gt;&lt;p&gt;Head over to Fazoora tab&amp;nbsp;and answer the question of the day&amp;nbsp;. Results are going to be calculated by the end of the month and you are the lucky winner . You are going get huge prize. Stay tuned for more fun stuff to come !&lt;/p&gt;&lt;p&gt;&lt;br&gt;&lt;/p&gt;" />
                  </pnp:CanvasControlProperties>
                </pnp:CanvasControl>
              </pnp:Controls>
            </pnp:Section>
            <pnp:Section Order="3" Type="TwoColumn">
              <pnp:Controls>
                <pnp:CanvasControl WebPartType="Text" ControlId="d65971aa-d00d-4747-bb24-08b86abee331" Order="1" Column="1">
                  <pnp:CanvasControlProperties>
                    <pnp:CanvasControlProperty Key="Text" Value="&lt;p&gt;&lt;br&gt;&lt;/p&gt;&lt;h2&gt;Ramadan decorations in CAIRO&lt;/h2&gt;&lt;p&gt;&lt;br&gt;&lt;/p&gt;&lt;p&gt;In Islamic history, you find that Egyptians are the first to invent the idea of the “Ramadan Lantern” where it dates back to the era of the Fatimid state to then move from Egypt to all countries of the world. The Fatimid caliph used to go out on the night before Ramadan along with children, each of them carrying a lantern to light the way as they sang in celebration for the holy month. In another story, one of the Fatimid caliphs ordered the lighting of mosques throughout the month of Ramadan with lanterns and candles.&lt;/p&gt;&lt;p&gt;&lt;br&gt;&lt;/p&gt;&lt;p&gt;Opinions may be conflicting, but everyone agrees that this tradition dates back at least several centuries. Certainly, it developed through the ages, and manifests itself in different forms, but we hope it retains its authenticity and remains a source of joy to our hearts.&lt;/p&gt;&lt;p&gt;&lt;br&gt;&lt;/p&gt;" />
                  </pnp:CanvasControlProperties>
                </pnp:CanvasControl>
                <pnp:CanvasControl WebPartType="Custom" JsonControlData="{&quot;id&quot;: &quot;544dd15b-cf3c-441b-96da-004d5a8cea1d&quot;, &quot;instanceId&quot;: &quot;a86e578f-f512-4c9e-ae1d-afa62670dc18&quot;, &quot;title&quot;: &quot;YouTube&quot;, &quot;description&quot;: &quot;YouTube&quot;, &quot;dataVersion&quot;: &quot;1.2&quot;, &quot;properties&quot;: {&quot;embedCode&quot;:&quot;&lt;iframe width=\&quot;560\&quot; height=\&quot;315\&quot; src=\&quot;https://www.youtube.com/embed/2aU61aKv18Y\&quot; frameborder=\&quot;0\&quot; allow=\&quot;accelerometer; autoplay; clipboard-write; encrypted-media; gyroscope; picture-in-picture\&quot; allowfullscreen=\&quot;\&quot;&gt;&lt;/iframe&gt;&quot;,&quot;shouldScaleWidth&quot;:true,&quot;runtimeState&quot;:{&quot;isPrivate&quot;:false,&quot;showControls&quot;:true,&quot;startTime&quot;:&quot;&quot;},&quot;thumbnailUrl&quot;:&quot;&quot;,&quot;cachedEmbedCode&quot;:&quot;&lt;iframe width=560 height=315 src=https://www.youtube.com/embed/2aU61aKv18Y frameborder=0 allow=accelerometer; autoplay; clipboard-write; encrypted-media; gyroscope; picture-in-picture allowfullscreen&gt; &lt;/iframe&gt;&quot;,&quot;cachedEmbedCodeThumbnail&quot;:&quot;&quot;}, &quot;serverProcessedContent&quot;: {&quot;htmlStrings&quot;:{},&quot;searchablePlainTexts&quot;:{},&quot;imageSources&quot;:{},&quot;links&quot;:{}}, &quot;dynamicDataPaths&quot;: {}, &quot;dynamicDataValues&quot;: {}}" ControlId="544dd15b-cf3c-441b-96da-004d5a8cea1d" Order="1" Column="2" />
              </pnp:Controls>
            </pnp:Section>
            <pnp:Section Order="4" Type="OneColumnFullWidth">
              <pnp:Controls>
                <pnp:CanvasControl WebPartType="Custom" JsonControlData="{&quot;id&quot;: &quot;62cac389-787f-495d-beca-e11786162ef4&quot;, &quot;instanceId&quot;: &quot;b55c7098-400b-48af-8ab0-d8348c23e98c&quot;, &quot;title&quot;: &quot;Countdown Timer&quot;, &quot;description&quot;: &quot;Countdown Timer&quot;, &quot;dataVersion&quot;: &quot;2.1&quot;, &quot;properties&quot;: {&quot;isFullWidth&quot;:true,&quot;showButton&quot;:false,&quot;countDate&quot;:&quot;Sun Feb 07 2021 07:30:00 GMT+0200 (Eastern European Standard Time)&quot;,&quot;description&quot;:&quot;&quot;,&quot;countDirection&quot;:&quot;COUNT_UP&quot;,&quot;dateDisplay&quot;:&quot;DAY_HOUR_MINUTE_SECOND&quot;,&quot;buttonText&quot;:&quot;&quot;,&quot;buttonURL&quot;:&quot;&quot;,&quot;backgroundImage&quot;:{&quot;focalPosition&quot;:{&quot;x&quot;:50,&quot;y&quot;:50},&quot;id&quot;:&quot;{fileuniqueid:SiteAssets/SitePages/Home/70624508Ramadan-delivery.jpg}&quot;,&quot;listId&quot;:&quot;{listid:Site Assets}&quot;,&quot;siteId&quot;:&quot;{sitecollectionid}&quot;,&quot;webId&quot;:&quot;{siteid}&quot;,&quot;zoomRatio&quot;:1,&quot;widthFactor&quot;:1.5009041591320071},&quot;backgroundOverlay&quot;:{&quot;color&quot;:&quot;#000000&quot;,&quot;opacity&quot;:60,&quot;useLightText&quot;:true}}, &quot;serverProcessedContent&quot;: {&quot;htmlStrings&quot;:{},&quot;searchablePlainTexts&quot;:{&quot;title&quot;:&quot;Count down to IFTAR&quot;},&quot;imageSources&quot;:{&quot;backgroundImage.url&quot;:&quot;{site}/SiteAssets/SitePages/Home/70624508Ramadan-delivery.jpg&quot;},&quot;links&quot;:{}}, &quot;dynamicDataPaths&quot;: {}, &quot;dynamicDataValues&quot;: {}}" ControlId="62cac389-787f-495d-beca-e11786162ef4" Order="1" Column="1" />
              </pnp:Controls>
            </pnp:Section>
            <pnp:Section Order="5" Type="OneColumn">
              <pnp:Controls>
                <pnp:CanvasControl WebPartType="ImageGallery" JsonControlData="{&quot;id&quot;: &quot;af8be689-990e-492a-81f7-ba3e4cd3ed9c&quot;, &quot;instanceId&quot;: &quot;421c2d20-d667-485d-b9ed-7f51b74f167a&quot;, &quot;title&quot;: &quot;Image gallery&quot;, &quot;description&quot;: &quot;Image gallery&quot;, &quot;dataVersion&quot;: &quot;1.8&quot;, &quot;properties&quot;: {&quot;layout&quot;:2,&quot;carouselSettings&quot;:{&quot;autoplay&quot;:false,&quot;autoplaySpeed&quot;:5,&quot;dots&quot;:false,&quot;lazyLoad&quot;:true,&quot;metadata&quot;:true,&quot;swipe&quot;:true},&quot;gridSettings&quot;:{&quot;imageSize&quot;:3,&quot;imageCropping&quot;:1,&quot;imageAspectRatio&quot;:2,&quot;lightbox&quot;:false},&quot;imageSourceType&quot;:1,&quot;isRecursive&quot;:false,&quot;isCdnEnabledForList&quot;:false,&quot;hasDynamicModeEnabled&quot;:false,&quot;maxImagesCount&quot;:10,&quot;images&quot;:[{&quot;description&quot;:&quot;&quot;,&quot;siteId&quot;:&quot;{sitecollectionid}&quot;,&quot;webId&quot;:&quot;{siteid}&quot;,&quot;listId&quot;:&quot;{listid:Site Assets}&quot;,&quot;id&quot;:&quot;{fileuniqueid:SiteAssets/SitePages/RamadanCalendar/157398fcb4406194c24cc63c46da662883043.jpg}&quot;,&quot;isInList&quot;:true,&quot;title&quot;:null,&quot;altText&quot;:&quot;&quot;,&quot;imageTileWidth&quot;:300},{&quot;description&quot;:&quot;&quot;,&quot;siteId&quot;:&quot;{sitecollectionid}&quot;,&quot;webId&quot;:&quot;{siteid}&quot;,&quot;listId&quot;:&quot;{listid:Site Assets}&quot;,&quot;id&quot;:&quot;{fileuniqueid:SiteAssets/SitePages/RamadanCalendar/2608mobile_banner.jpg}&quot;,&quot;isInList&quot;:true,&quot;title&quot;:null,&quot;altText&quot;:&quot;&quot;,&quot;minCanvasWidth&quot;:32767,&quot;imageTileWidth&quot;:300},{&quot;description&quot;:&quot;&quot;,&quot;siteId&quot;:&quot;{sitecollectionid}&quot;,&quot;webId&quot;:&quot;{siteid}&quot;,&quot;listId&quot;:&quot;{listid:Site Assets}&quot;,&quot;id&quot;:&quot;{fileuniqueid:SiteAssets/SitePages/RamadanCalendar/745414elHFkW.jpg}&quot;,&quot;isInList&quot;:true,&quot;title&quot;:null,&quot;altText&quot;:&quot;&quot;,&quot;minCanvasWidth&quot;:32767,&quot;imageTileWidth&quot;:300},{&quot;description&quot;:&quot;&quot;,&quot;siteId&quot;:&quot;{sitecollectionid}&quot;,&quot;webId&quot;:&quot;{siteid}&quot;,&quot;listId&quot;:&quot;{listid:Site Assets}&quot;,&quot;id&quot;:&quot;{fileuniqueid:SiteAssets/SitePages/RamadanCalendar/80488WhatsApp-Image-2018-10-18-at-8.06.23-PM.jpeg}&quot;,&quot;isInList&quot;:true,&quot;title&quot;:null,&quot;altText&quot;:&quot;&quot;,&quot;minCanvasWidth&quot;:32767,&quot;imageTileWidth&quot;:300}],&quot;canAlwaysSelectDocLibAsSource&quot;:false,&quot;layoutComponentId&quot;:&quot;&quot;}, &quot;serverProcessedContent&quot;: {&quot;htmlStrings&quot;:{},&quot;searchablePlainTexts&quot;:{&quot;title&quot;:&quot;Ramadan Offers &quot;},&quot;imageSources&quot;:{&quot;images[0].url&quot;:&quot;{site}/SiteAssets/SitePages/RamadanCalendar/157398fcb4406194c24cc63c46da662883043.jpg&quot;,&quot;images[1].url&quot;:&quot;{site}/SiteAssets/SitePages/RamadanCalendar/2608mobile_banner.jpg&quot;,&quot;images[2].url&quot;:&quot;{site}/SiteAssets/SitePages/RamadanCalendar/745414elHFkW.jpg&quot;,&quot;images[3].url&quot;:&quot;{site}/SiteAssets/SitePages/RamadanCalendar/80488WhatsApp-Image-2018-10-18-at-8.06.23-PM.jpeg&quot;},&quot;links&quot;:{},&quot;customMetadata&quot;:{&quot;images[0].url&quot;:{&quot;siteId&quot;:&quot;{sitecollectionid}&quot;,&quot;webId&quot;:&quot;{siteid}&quot;,&quot;listId&quot;:&quot;{listid:Site Assets}&quot;,&quot;uniqueId&quot;:&quot;{fileuniqueid:SiteAssets/SitePages/RamadanCalendar/157398fcb4406194c24cc63c46da662883043.jpg}&quot;,&quot;fixedWidth&quot;:300},&quot;images[1].url&quot;:{&quot;siteId&quot;:&quot;{sitecollectionid}&quot;,&quot;webId&quot;:&quot;{siteid}&quot;,&quot;listId&quot;:&quot;{listid:Site Assets}&quot;,&quot;uniqueId&quot;:&quot;{fileuniqueid:SiteAssets/SitePages/RamadanCalendar/2608mobile_banner.jpg}&quot;,&quot;fixedWidth&quot;:300,&quot;minCanvasWidth&quot;:32767},&quot;images[2].url&quot;:{&quot;siteId&quot;:&quot;{sitecollectionid}&quot;,&quot;webId&quot;:&quot;{siteid}&quot;,&quot;listId&quot;:&quot;{listid:Site Assets}&quot;,&quot;uniqueId&quot;:&quot;{fileuniqueid:SiteAssets/SitePages/RamadanCalendar/745414elHFkW.jpg}&quot;,&quot;fixedWidth&quot;:300,&quot;minCanvasWidth&quot;:32767},&quot;images[3].url&quot;:{&quot;siteId&quot;:&quot;{sitecollectionid}&quot;,&quot;webId&quot;:&quot;{siteid}&quot;,&quot;listId&quot;:&quot;{listid:Site Assets}&quot;,&quot;uniqueId&quot;:&quot;{fileuniqueid:SiteAssets/SitePages/RamadanCalendar/80488WhatsApp-Image-2018-10-18-at-8.06.23-PM.jpeg}&quot;,&quot;fixedWidth&quot;:300,&quot;minCanvasWidth&quot;:32767}}}, &quot;dynamicDataPaths&quot;: {}, &quot;dynamicDataValues&quot;: {}}" ControlId="af8be689-990e-492a-81f7-ba3e4cd3ed9c" Order="1" Column="1" />
              </pnp:Controls>
            </pnp:Section>
          </pnp:Sections>
        </pnp:ClientSidePage>
        <pnp:ClientSidePage PromoteAsNewsArticle="false" PromoteAsTemplate="false" Overwrite="true" Title="Mac n Cheese" ThumbnailUrl="" PageName="Mac-n-Cheese.aspx">
          <pnp:Header Type="Custom" ServerRelativeImageUrl="{site}/SiteAssets/SitePages/Mac-n-Cheese/94877-chicago-foodie-girl--Southport-and-Irving--SIP-.jpeg" TranslateX="51.0356255178128" TranslateY="49.5614035087719" LayoutType="FullWidthImage" TextAlignment="Center" ShowTopicHeader="false" ShowPublishDate="false" TopicHeader="TEXT ABOVE TITLE" AlternativeText="" Authors="[]" AuthorByLine="[]" AuthorByLineId="-1" />
          <pnp:Sections>
            <pnp:Section Order="1" Type="TwoColumn">
              <pnp:Controls>
                <pnp:CanvasControl WebPartType="Text" ControlId="41446835-0080-4b7f-be54-8cf30216334b" Order="1" Column="1">
                  <pnp:CanvasControlProperties>
                    <pnp:CanvasControlProperty Key="Text" Value="&lt;p&gt;&lt;/p&gt;&lt;h2&gt;Nutrition Facts&lt;/h2&gt;&lt;p&gt;Per Serving:&lt;/p&gt;&lt;p&gt;630 calories; protein 26.5g 53% DV; carbohydrates 55g 18% DV; fat 33.6g 52% DV; cholesterol 99.6mg 33% DV; sodium 777mg 31% DV.&lt;/p&gt;&lt;p&gt;&lt;/p&gt;" />
                  </pnp:CanvasControlProperties>
                </pnp:CanvasControl>
                <pnp:CanvasControl WebPartType="Text" ControlId="7b0ff37e-6f3d-416b-bfb7-376cd290dd5a" Order="1" Column="2">
                  <pnp:CanvasControlProperties>
                    <pnp:CanvasControlProperty Key="Text" Value="&lt;p&gt;&lt;strong&gt;Total&amp;nbsp;Time&lt;/strong&gt;&lt;/p&gt;&lt;p&gt;15 minutes&lt;/p&gt;&lt;p&gt;&lt;strong&gt;Prep&amp;nbsp;Time&lt;/strong&gt;&lt;/p&gt;&lt;p&gt;5 minutes&lt;/p&gt;&lt;p&gt;&lt;strong&gt;Cook&amp;nbsp;Time&lt;/strong&gt;&lt;/p&gt;&lt;p&gt;10 minutes&lt;/p&gt;" />
                  </pnp:CanvasControlProperties>
                </pnp:CanvasControl>
              </pnp:Controls>
            </pnp:Section>
            <pnp:Section Order="2" Type="TwoColumn">
              <pnp:Controls>
                <pnp:CanvasControl WebPartType="Text" ControlId="70a89332-ab7f-4b70-8556-5865367acd17" Order="1" Column="1">
                  <pnp:CanvasControlProperties>
                    <pnp:CanvasControlProperty Key="Text" Value="&lt;p&gt;&lt;/p&gt;&lt;h2&gt;Preparation&lt;/h2&gt;&lt;ol&gt;&lt;li&gt;In a large pot, bring the milk to a boil.&lt;/li&gt;&lt;li&gt;Add the pasta and stir constantly until the pasta is cooked, about 10 minutes.&lt;/li&gt;&lt;li&gt;Turn off the heat, then add the cheddar. Stir until the cheese is melted and the pasta is evenly coated.&lt;/li&gt;&lt;li&gt;Enjoy!&lt;/li&gt;&lt;/ol&gt;&lt;p&gt;&lt;/p&gt;" />
                  </pnp:CanvasControlProperties>
                </pnp:CanvasControl>
                <pnp:CanvasControl WebPartType="Custom" JsonControlData="{&quot;id&quot;: &quot;544dd15b-cf3c-441b-96da-004d5a8cea1d&quot;, &quot;instanceId&quot;: &quot;d9c08857-bec6-4d8b-a12b-32a7ab9fefeb&quot;, &quot;title&quot;: &quot;YouTube&quot;, &quot;description&quot;: &quot;YouTube&quot;, &quot;dataVersion&quot;: &quot;1.2&quot;, &quot;properties&quot;: {&quot;embedCode&quot;:&quot;https://www.youtube.com/watch?v=snsEjQKO-s8&quot;,&quot;shouldScaleWidth&quot;:true,&quot;runtimeState&quot;:{&quot;isPrivate&quot;:false,&quot;showControls&quot;:true},&quot;thumbnailUrl&quot;:&quot;https://www.bing.com/th?id=OVT.VF_IsPrxvF_hJKnWA_1606685089&amp;pid=Api&quot;,&quot;cachedEmbedCode&quot;:&quot;&lt;iframe width=1280 height=720 src=https://www.youtube.com/embed/snsEjQKO-s8?autoplay=0 frameborder=0 allowfullscreen&gt; &lt;/iframe&gt;&quot;,&quot;cachedEmbedCodeThumbnail&quot;:&quot;https://www.bing.com/th?id=OVT.VF_IsPrxvF_hJKnWA_1606685089&amp;pid=Api&quot;}, &quot;serverProcessedContent&quot;: {&quot;htmlStrings&quot;:{},&quot;searchablePlainTexts&quot;:{},&quot;imageSources&quot;:{},&quot;links&quot;:{}}, &quot;dynamicDataPaths&quot;: {}, &quot;dynamicDataValues&quot;: {}}" ControlId="544dd15b-cf3c-441b-96da-004d5a8cea1d" Order="1" Column="2" />
              </pnp:Controls>
            </pnp:Section>
          </pnp:Sections>
        </pnp:ClientSidePage>
        <pnp:ClientSidePage PromoteAsNewsArticle="false" PromoteAsTemplate="false" Overwrite="true" Title="“When we give cheerfully and accept gratefully, everyone is blessed.”" ThumbnailUrl="" PageName="Donate.aspx">
          <pnp:Header Type="Custom" ServerRelativeImageUrl="{site}/SiteAssets/SitePages/Donate/63981-Ramadan-Kareem-Free-Stock-Photo---Public-Domain-Pictures.jpeg" TranslateX="43.8267614738203" TranslateY="21.5555555555556" LayoutType="ColorBlock" TextAlignment="Center" ShowTopicHeader="false" ShowPublishDate="false" TopicHeader="" AlternativeText="" Authors="[]" AuthorByLine="[]" AuthorByLineId="-1" />
          <pnp:Sections>
            <pnp:Section Order="1" Type="OneColumnFullWidth">
              <pnp:Controls>
                <pnp:CanvasControl WebPartType="Hero" JsonControlData="{&quot;id&quot;: &quot;c4bd7b2f-7b6e-4599-8485-16504575f590&quot;, &quot;instanceId&quot;: &quot;6932a264-ba1f-4477-acbb-560bb966973f&quot;, &quot;title&quot;: &quot;Hero&quot;, &quot;description&quot;: &quot;Hero&quot;, &quot;dataVersion&quot;: &quot;1.5&quot;, &quot;properties&quot;: {&quot;heroLayoutThreshold&quot;:640,&quot;carouselLayoutMaxWidth&quot;:639,&quot;isFullWidth&quot;:true,&quot;layoutCategory&quot;:2,&quot;layout&quot;:5,&quot;content&quot;:[{&quot;id&quot;:&quot;ceb42287-9636-4855-96f0-3a22c2489fd3&quot;,&quot;type&quot;:&quot;UrlLink&quot;,&quot;color&quot;:4,&quot;image&quot;:{&quot;zoomRatio&quot;:0.80190000000000017,&quot;siteId&quot;:&quot;{sitecollectionid}&quot;,&quot;webId&quot;:&quot;{siteid}&quot;,&quot;listId&quot;:&quot;{listid:Site Assets}&quot;,&quot;id&quot;:&quot;{fileuniqueid:SiteAssets/SitePages/Donate/933364814Slider-810x425pix.jpg}&quot;,&quot;imageUrl&quot;:&quot;https://{fqdn}/_api/v2.1/sites/{fqdn},{sitecollectionid},{siteid}/lists/{listid:Site Assets}/items/{fileuniqueid:SiteAssets/SitePages/Donate/933364814Slider-810x425pix.jpg}/driveItem/thumbnails/0/c400x99999/content?preferNoRedirect=true&amp;prefer=extendCacheMaxAge&amp;clientType=modernWebPart&quot;,&quot;widthFactor&quot;:0.58,&quot;minCanvasWidth&quot;:1},&quot;description&quot;:&quot; non-profit development institution established in 2007 with the objective of developing the Egyptian individual in a comprehensive manner.&quot;,&quot;showDescription&quot;:true,&quot;showTitle&quot;:true,&quot;alternateText&quot;:&quot;&quot;,&quot;imageDisplayOption&quot;:3,&quot;isDefaultImage&quot;:false,&quot;showCallToAction&quot;:true,&quot;isDefaultImageLoaded&quot;:false,&quot;isCustomImageLoaded&quot;:true,&quot;showFeatureText&quot;:false,&quot;previewImage&quot;:{&quot;zoomRatio&quot;:1,&quot;imageUrl&quot;:&quot;&quot;,&quot;widthFactor&quot;:0.25,&quot;minCanvasWidth&quot;:32767},&quot;upperCaseCallToAction&quot;:false},{&quot;id&quot;:&quot;2b4b0673-e5e0-4f12-a77b-ccf326af8820&quot;,&quot;type&quot;:&quot;UrlLink&quot;,&quot;color&quot;:4,&quot;description&quot;:&quot; non-profit, non-governmental organization providing free world-class medical services to the less privileged in Egypt and throughout the region in the field of cardiovascular diseases.&quot;,&quot;showDescription&quot;:true,&quot;showTitle&quot;:true,&quot;alternateText&quot;:&quot;&quot;,&quot;imageDisplayOption&quot;:1,&quot;isDefaultImage&quot;:false,&quot;showCallToAction&quot;:true,&quot;isDefaultImageLoaded&quot;:true,&quot;isCustomImageLoaded&quot;:false,&quot;showFeatureText&quot;:false,&quot;previewImage&quot;:{&quot;zoomRatio&quot;:0.38742048900000015,&quot;imageUrl&quot;:&quot;https://myglobalheart.org/wp-content/uploads/2020/04/together-1024x288.png&quot;,&quot;widthFactor&quot;:0.58,&quot;minCanvasWidth&quot;:640},&quot;upperCaseCallToAction&quot;:false},{&quot;id&quot;:&quot;067c3c85-bde5-4601-a7b9-7b87150dfdcc&quot;,&quot;type&quot;:&quot;UrlLink&quot;,&quot;color&quot;:4,&quot;description&quot;:&quot;Established in 1999 as a youth movement at Cairo University and Sherif Abd Al Azim, an engineering professor, supervised the movement.\n\n&quot;,&quot;showDescription&quot;:true,&quot;showTitle&quot;:true,&quot;alternateText&quot;:&quot;&quot;,&quot;imageDisplayOption&quot;:1,&quot;isDefaultImage&quot;:false,&quot;showCallToAction&quot;:true,&quot;isDefaultImageLoaded&quot;:true,&quot;isCustomImageLoaded&quot;:false,&quot;showFeatureText&quot;:false,&quot;previewImage&quot;:{&quot;zoomRatio&quot;:1,&quot;imageUrl&quot;:&quot;https://resala.org/wp-content/uploads/2019/12/%D8%A7%D9%84%D8%AA%D8%A8%D8%B1%D8%B9.jpg&quot;,&quot;widthFactor&quot;:0.58,&quot;minCanvasWidth&quot;:640}},{&quot;id&quot;:&quot;e29c304d-fedf-47cf-9f09-9b3cb9825a58&quot;,&quot;type&quot;:&quot;UrlLink&quot;,&quot;color&quot;:4,&quot;description&quot;:&quot;The Hospital Will Be Built Upon 35-Acres In Sheikh Zayed City, Giza. It Will Include A Fully Integrated Hospital Building To Treat All Types Of Tumors.&quot;,&quot;showDescription&quot;:true,&quot;showTitle&quot;:true,&quot;alternateText&quot;:&quot;&quot;,&quot;imageDisplayOption&quot;:1,&quot;isDefaultImage&quot;:false,&quot;showCallToAction&quot;:true,&quot;isDefaultImageLoaded&quot;:true,&quot;isCustomImageLoaded&quot;:false,&quot;showFeatureText&quot;:false,&quot;previewImage&quot;:{&quot;zoomRatio&quot;:0.72900000000000009,&quot;imageUrl&quot;:&quot;https://500500egypt.org/newstorage/sections/February2020/ONrybuPSB4h9zOC7UbTm.jpg&quot;,&quot;widthFactor&quot;:0.58,&quot;minCanvasWidth&quot;:640}},{&quot;id&quot;:&quot;1c0c8c8a-dcc5-40d8-a165-814f74d59faf&quot;,&quot;type&quot;:&quot;UrlLink&quot;,&quot;color&quot;:4,&quot;image&quot;:{&quot;zoomRatio&quot;:1,&quot;siteId&quot;:&quot;{sitecollectionid}&quot;,&quot;webId&quot;:&quot;{siteid}&quot;,&quot;listId&quot;:&quot;{listid:Site Assets}&quot;,&quot;id&quot;:&quot;{fileuniqueid:SiteAssets/SitePages/Donate/3418061374donation-to-57357-hospital.jpg}&quot;,&quot;imageUrl&quot;:&quot;https://{fqdn}/_api/v2.1/sites/{fqdn},{sitecollectionid},{siteid}/lists/{listid:Site Assets}/items/{fileuniqueid:SiteAssets/SitePages/Donate/3418061374donation-to-57357-hospital.jpg}/driveItem/thumbnails/0/c400x99999/content?preferNoRedirect=true&amp;prefer=extendCacheMaxAge&amp;clientType=modernWebPart&quot;,&quot;widthFactor&quot;:0.58,&quot;minCanvasWidth&quot;:640},&quot;description&quot;:&quot;a unique healthcare institution and an ultimate example of what can be achieved when people work together for a common goal. The people of Egypt and friends from all over the world and most particularly in the Arab World have contributed generously to the establishment of the hospital which has been completely built by donations. &quot;,&quot;showDescription&quot;:true,&quot;showTitle&quot;:true,&quot;alternateText&quot;:&quot;&quot;,&quot;imageDisplayOption&quot;:3,&quot;isDefaultImage&quot;:false,&quot;showCallToAction&quot;:true,&quot;isDefaultImageLoaded&quot;:false,&quot;isCustomImageLoaded&quot;:true,&quot;showFeatureText&quot;:false,&quot;previewImage&quot;:{&quot;zoomRatio&quot;:0.98010000000000019,&quot;imageUrl&quot;:&quot;&quot;,&quot;widthFactor&quot;:0.25,&quot;minCanvasWidth&quot;:32767},&quot;upperCaseCallToAction&quot;:false}]}, &quot;serverProcessedContent&quot;: {&quot;htmlStrings&quot;:{},&quot;searchablePlainTexts&quot;:{&quot;content[0].title&quot;:&quot;Misr El Kheir Foundation (MEK) &quot;,&quot;content[1].title&quot;:&quot;Magdi Yacoub Heart Foundation (MYF)&quot;,&quot;content[2].title&quot;:&quot;Resala&quot;,&quot;content[3].title&quot;:&quot;500500 hospital&quot;,&quot;content[4].title&quot;:&quot;57357 hospital&quot;,&quot;content[0].callToActionText&quot;:&quot;Donate&quot;,&quot;content[1].callToActionText&quot;:&quot;Donate&quot;,&quot;content[2].callToActionText&quot;:&quot;Learn more&quot;,&quot;content[3].callToActionText&quot;:&quot;Learn more&quot;,&quot;content[4].callToActionText&quot;:&quot;Donate&quot;},&quot;imageSources&quot;:{&quot;content[0].image.url&quot;:&quot;{site}/SiteAssets/SitePages/Donate/933364814Slider-810x425pix.jpg&quot;,&quot;content[4].image.url&quot;:&quot;{site}/SiteAssets/SitePages/Donate/3418061374donation-to-57357-hospital.jpg&quot;,&quot;content[0].previewImage.url&quot;:&quot;https://misrelkheir.org/winter/?gclid=Cj0KCQiAzZL-BRDnARIsAPCJs7333uVtxNFxLI6355N3nESI9HHRNro8WbAnGU4rDwWRUNh_wkPrfNgaAn_DEALw_wcB&quot;,&quot;content[1].previewImage.url&quot;:&quot;https://myglobalheart.org/donate/&quot;,&quot;content[2].previewImage.url&quot;:&quot;https://resala.org/donat/&quot;,&quot;content[3].previewImage.url&quot;:&quot;https://500500egypt.org/?gclid=Cj0KCQiAzZL-BRDnARIsAPCJs70ZEiRH2U4dOc61XHcruXV6qhG53HXVKoPikByw8rSB0xZJw_5Ko8gaAuwFEALw_wcB&quot;,&quot;content[4].previewImage.url&quot;:&quot;https://give.57357.org/&quot;},&quot;links&quot;:{&quot;content[0].link&quot;:&quot;https://misrelkheir.org/winter/?gclid=Cj0KCQiAzZL-BRDnARIsAPCJs7333uVtxNFxLI6355N3nESI9HHRNro8WbAnGU4rDwWRUNh_wkPrfNgaAn_DEALw_wcB&quot;,&quot;content[1].link&quot;:&quot;https://myglobalheart.org/donate/&quot;,&quot;content[2].link&quot;:&quot;https://resala.org/donat/&quot;,&quot;content[3].link&quot;:&quot;https://500500egypt.org/?gclid=Cj0KCQiAzZL-BRDnARIsAPCJs70ZEiRH2U4dOc61XHcruXV6qhG53HXVKoPikByw8rSB0xZJw_5Ko8gaAuwFEALw_wcB&quot;,&quot;content[4].link&quot;:&quot;https://give.57357.org/&quot;},&quot;customMetadata&quot;:{&quot;content[0].image.url&quot;:{&quot;siteId&quot;:&quot;{sitecollectionid}&quot;,&quot;webId&quot;:&quot;{siteid}&quot;,&quot;listId&quot;:&quot;{listid:Site Assets}&quot;,&quot;uniqueId&quot;:&quot;{fileuniqueid:SiteAssets/SitePages/Donate/933364814Slider-810x425pix.jpg}&quot;,&quot;renderWidthRatio&quot;:0.58,&quot;renderWidthRatioThreshold&quot;:640,&quot;minCanvasWidth&quot;:1},&quot;content[4].image.url&quot;:{&quot;siteId&quot;:&quot;{sitecollectionid}&quot;,&quot;webId&quot;:&quot;{siteid}&quot;,&quot;listId&quot;:&quot;{listid:Site Assets}&quot;,&quot;uniqueId&quot;:&quot;{fileuniqueid:SiteAssets/SitePages/Donate/3418061374donation-to-57357-hospital.jpg}&quot;,&quot;renderWidthRatio&quot;:0.58,&quot;renderWidthRatioThreshold&quot;:640,&quot;minCanvasWidth&quot;:640},&quot;content[0].previewImage.url&quot;:{&quot;renderWidthRatio&quot;:0.25,&quot;renderWidthRatioThreshold&quot;:640,&quot;minCanvasWidth&quot;:32767},&quot;content[1].previewImage.url&quot;:{&quot;renderWidthRatio&quot;:0.58,&quot;renderWidthRatioThreshold&quot;:640,&quot;minCanvasWidth&quot;:640},&quot;content[2].previewImage.url&quot;:{&quot;renderWidthRatio&quot;:0.58,&quot;renderWidthRatioThreshold&quot;:640,&quot;minCanvasWidth&quot;:640},&quot;content[3].previewImage.url&quot;:{&quot;renderWidthRatio&quot;:0.58,&quot;renderWidthRatioThreshold&quot;:640,&quot;minCanvasWidth&quot;:640},&quot;content[4].previewImage.url&quot;:{&quot;renderWidthRatio&quot;:0.25,&quot;renderWidthRatioThreshold&quot;:640,&quot;minCanvasWidth&quot;:32767},&quot;heroLayoutComponentId&quot;:{&quot;minCanvasWidth&quot;:640},&quot;carouselLayoutComponentId&quot;:{&quot;maxCanvasWidth&quot;:639}},&quot;componentDependencies&quot;:{&quot;heroLayoutComponentId&quot;:&quot;9586b262-54de-4b27-9eb9-34c671400c33&quot;,&quot;carouselLayoutComponentId&quot;:&quot;8ac0c53c-e8d0-4e3e-87d0-7449eb0d4027&quot;}}, &quot;dynamicDataPaths&quot;: {}, &quot;dynamicDataValues&quot;: {}}" ControlId="c4bd7b2f-7b6e-4599-8485-16504575f590" Order="1" Column="1" />
              </pnp:Controls>
            </pnp:Section>
          </pnp:Sections>
        </pnp:ClientSidePage>
        <pnp:ClientSidePage PromoteAsNewsArticle="false" PromoteAsTemplate="false" Overwrite="true" Title="Every day a new Riddle" ThumbnailUrl="" PageName="Fazoora.aspx">
          <pnp:Header Type="Custom" ServerRelativeImageUrl="{site}/SiteAssets/SitePages/Fazoora/57327-decoration-3346133_1920.jpg" TranslateX="53.1068765534383" TranslateY="23.7777777777778" LayoutType="ColorBlock" TextAlignment="Center" ShowTopicHeader="false" ShowPublishDate="false" TopicHeader="TEXT ABOVE TITLE" AlternativeText="" Authors="[]" AuthorByLine="[]" AuthorByLineId="-1" />
          <pnp:Sections>
            <pnp:Section Order="1" Type="TwoColumn">
              <pnp:Controls>
                <pnp:CanvasControl WebPartType="Text" ControlId="885446ca-fe96-4b11-8cb6-c0b1beaf3218" Order="1" Column="1">
                  <pnp:CanvasControlProperties>
                    <pnp:CanvasControlProperty Key="Text" Value="&lt;p&gt;&lt;br&gt;&lt;/p&gt;&lt;h2&gt;Ramadan Quiz&lt;/h2&gt;&lt;p&gt;Every day we are going to post a new question . By End of Ramadan we are going to announce&amp;nbsp;the winner.&lt;/p&gt;&lt;p&gt;&lt;br&gt;&lt;/p&gt;&lt;p&gt;1st Place will get 5000 Egyptian Pounds.&lt;/p&gt;&lt;p&gt;2nd Place will get two days vacation to Maldives.&lt;/p&gt;&lt;p&gt;Third Place will get free two cinema tickets.&lt;/p&gt;&lt;p&gt;&lt;br&gt;&lt;/p&gt;" />
                  </pnp:CanvasControlProperties>
                </pnp:CanvasControl>
                <pnp:CanvasControl WebPartType="Text" ControlId="a01d39d9-3a55-4d67-8613-04baf8a92265" Order="1" Column="2">
                  <pnp:CanvasControlProperties>
                    <pnp:CanvasControlProperty Key="Text" Value="&lt;p&gt;&lt;br&gt;&lt;/p&gt;&lt;h2&gt;Rules of the Quiz&lt;/h2&gt;&lt;p&gt;&lt;br&gt;&lt;/p&gt;&lt;p&gt;Every employee has only one chance to submit his answer.&amp;nbsp;&lt;/p&gt;&lt;p&gt;Every day you will get a new question.&lt;/p&gt;&lt;p&gt;&lt;br&gt;&lt;/p&gt;" />
                  </pnp:CanvasControlProperties>
                </pnp:CanvasControl>
              </pnp:Controls>
            </pnp:Section>
            <pnp:Section Order="2" Type="TwoColumn">
              <pnp:Controls>
                <pnp:CanvasControl WebPartType="Text" ControlId="939ca001-db00-446c-995f-ca527d46b696" Order="1" Column="1">
                  <pnp:CanvasControlProperties>
                    <pnp:CanvasControlProperty Key="Text" Value="&lt;p&gt;&lt;br&gt;&lt;/p&gt;&lt;h2&gt;Ready for today's question ?&lt;/h2&gt;&lt;p&gt;&lt;br&gt;&lt;/p&gt;&lt;p&gt;&lt;br&gt;&lt;/p&gt;&lt;p&gt;&lt;br&gt;&lt;/p&gt;" />
                  </pnp:CanvasControlProperties>
                </pnp:CanvasControl>
                <pnp:CanvasControl WebPartType="Custom" JsonControlData="{&quot;id&quot;: &quot;9d7e898c-f1bb-473a-9ace-8b415036578b&quot;, &quot;instanceId&quot;: &quot;6d06262c-8bf2-4bf2-a325-a1053c013bb8&quot;, &quot;title&quot;: &quot;Microsoft PowerApps (Preview)&quot;, &quot;description&quot;: &quot;Microsoft PowerApps (Preview)&quot;, &quot;dataVersion&quot;: &quot;1.0&quot;, &quot;properties&quot;: {&quot;powerAppId&quot;:&quot;dcc83a24-48ed-4df1-a850-a29d8b486f58&quot;,&quot;shouldScaleWidth&quot;:true,&quot;powerAppSizing&quot;:3,&quot;customWidth&quot;:384,&quot;customHeight&quot;:681.6,&quot;paInput&quot;:&quot;https://apps.preview.powerapps.com/play/dcc83a24-48ed-4df1-a850-a29d8b486f58?tenantId=63936d84-2f02-4294-8c25-f57da11b1ed5&quot;,&quot;queryParameters&quot;:{&quot;tenantId&quot;:&quot;63936d84-2f02-4294-8c25-f57da11b1ed5&quot;},&quot;aspectRatio&quot;:0.56338028169014087,&quot;width&quot;:384,&quot;height&quot;:681.6,&quot;backgroundColor&quot;:&quot;rgba(0, 176, 240, 1)&quot;}, &quot;serverProcessedContent&quot;: {&quot;htmlStrings&quot;:{},&quot;searchablePlainTexts&quot;:{},&quot;imageSources&quot;:{},&quot;links&quot;:{}}, &quot;dynamicDataPaths&quot;: {}, &quot;dynamicDataValues&quot;: {}}" ControlId="9d7e898c-f1bb-473a-9ace-8b415036578b" Order="2" Column="1" />
              </pnp:Controls>
            </pnp:Section>
          </pnp:Sections>
        </pnp:ClientSidePage>
        <pnp:ClientSidePage PromoteAsNewsArticle="false" PromoteAsTemplate="false" Overwrite="true" EnableComments="false" Title="Ramadan Wall" ThumbnailUrl="" PageName="Share-your-dish.aspx">
          <pnp:Header Type="Custom" ServerRelativeImageUrl="https://{fqdn}{site}/SiteAssets/SitePages/Home/70624508Ramadan-delivery.jpg" LayoutType="CutInShape" TextAlignment="Center" ShowTopicHeader="false" ShowPublishDate="false" TopicHeader="" AlternativeText="" Authors="[]" AuthorByLine="[]" AuthorByLineId="-1" />
          <pnp:Sections>
            <pnp:Section Order="1" Type="OneColumn">
              <pnp:Controls>
                <pnp:CanvasControl WebPartType="Text" ControlId="fad21d3b-43fe-4591-9394-6187525df8ed" Order="1" Column="1">
                  <pnp:CanvasControlProperties>
                    <pnp:CanvasControlProperty Key="Text" Value="&lt;p&gt;Do you have a charity project and looking for volunteers ? Share it now on Ramadan Wall&lt;/p&gt;&lt;p&gt;Do you want to share some tips regarding Ramadan ? Share it now on Ramadan Wall&lt;/p&gt;&lt;p&gt;Did you cook a delicious dish yesterday and want to share the recipe ? Share it now Ramadan Wall&lt;/p&gt;" />
                  </pnp:CanvasControlProperties>
                </pnp:CanvasControl>
              </pnp:Controls>
            </pnp:Section>
            <pnp:Section Order="2" Type="OneColumn">
              <pnp:Controls>
                <pnp:CanvasControl WebPartType="Custom" JsonControlData="{&quot;id&quot;: &quot;cb3bfe97-a47f-47ca-bffb-bb9a5ff83d75&quot;, &quot;instanceId&quot;: &quot;bb6432b2-fe70-485e-b742-8ddaa1316886&quot;, &quot;title&quot;: &quot;Conversations&quot;, &quot;description&quot;: &quot;Conversations&quot;, &quot;dataVersion&quot;: &quot;1.0&quot;, &quot;properties&quot;: {&quot;id&quot;:&quot;eyJfdHlwZSI6Ikdyb3VwIiwiaWQiOiI3NzgzODc0NTYxIn0&quot;,&quot;threadCount&quot;:12,&quot;type&quot;:&quot;Group&quot;}, &quot;serverProcessedContent&quot;: {&quot;htmlStrings&quot;:{},&quot;searchablePlainTexts&quot;:{},&quot;imageSources&quot;:{},&quot;links&quot;:{}}, &quot;dynamicDataPaths&quot;: {}, &quot;dynamicDataValues&quot;: {}}" ControlId="cb3bfe97-a47f-47ca-bffb-bb9a5ff83d75" Order="1" Column="1" />
              </pnp:Controls>
            </pnp:Section>
          </pnp:Sections>
        </pnp:ClientSidePage>
      </pnp:ClientSidePages>
    </pnp:ProvisioningTemplate>
  </pnp:Templates>
</pnp:Provisioning>